WebtoonHooks/__init__.py
WebtoonHooks/embed.py
WebtoonHooks/webtoon.py
WebtoonHooks-2.0.2.dist-info/METADATA
WebtoonHooks-2.0.2.dist-info/WHEEL
WebtoonHooks-2.0.2.dist-info/top_level.txt
WebtoonHooks-2.0.2.dist-info/RECORD
