Metadata-Version: 2.1
Name: WebtoonHooks
Version: 2.0.2
Summary: Send discord webhooks with all the daily releases from webtoon
Home-page: https://github.com/MissLummie/webtoons-discord
Author: Aluma Gelbard
Author-email: violetaluma@hotmail.com
License: UNKNOWN
Platform: UNKNOWN
Requires-Dist: DiscordHooks
Requires-Dist: beautifulsoup4
Requires-Dist: requests
Requires-Dist: lxml
